time_lapse/__init__.py
time_lapse/cli.py
time_lapse/detect_audio.py
time_lapse/output.py
time_lapse/py.typed
time_lapse/source.py
time_lapse/thumbnail.py
time_lapse/watermark.py
time_lapse/fonts/Jost-400-Book.ttf
time_lapse/fonts/LICENSE.md
time_lapse-9.0.dist-info/entry_points.txt
time_lapse-9.0.dist-info/LICENSE
time_lapse-9.0.dist-info/WHEEL
time_lapse-9.0.dist-info/METADATA
time_lapse-9.0.dist-info/RECORD
