Metadata-Version: 2.3
Name: time-lapse
Version: 9.0
Summary: Time-lapse movie assembly
Keywords: ffmpeg,photography,time-lapse
Author-email: Arne de Laat <arne@delaat.net>
Maintainer-email: Arne de Laat <arne@delaat.net>
Requires-Python: >=3.13
Classifier: Intended Audience :: Developers
Classifier: Intended Audience :: Other Audience
Classifier: License :: OSI Approved :: MIT License
Classifier: Programming Language :: Python
Classifier: Programming Language :: Python :: 3
Classifier: Topic :: Multimedia :: Video :: Conversion
Requires-Dist: ffmpeg-python==0.2.0
Requires-Dist: pillow==11.0.0
Requires-Dist: coverage==7.6.10 ; extra == "dev"
Requires-Dist: mypy==1.14.1 ; extra == "dev"
Requires-Dist: graphviz ; extra == "graph"
Requires-Dist: flit==3.10.1 ; extra == "publish"
Project-URL: Homepage, https://arne.delaat.net/timelapse.html
Project-URL: Repository, https://github.com/153957/time-lapse
Provides-Extra: dev
Provides-Extra: graph
Provides-Extra: publish
